spacefill/__init__.py
spacefill/curvetools.py
spacefill/spacefill.py
spacefill-0.1.1.dist-info/DESCRIPTION.rst
spacefill-0.1.1.dist-info/METADATA
spacefill-0.1.1.dist-info/RECORD
spacefill-0.1.1.dist-info/WHEEL
spacefill-0.1.1.dist-info/metadata.json
spacefill-0.1.1.dist-info/top_level.txt
